LICENSE.md
MANIFEST.in
README.rst
setup.cfg
setup.py
fastools/__init__.py
fastools/cli.py
fastools/fastools.py
fastools/peeker.py
fastools/setup.cfg
fastools/split_fasta.py
fastools/utils.py
fastools.egg-info/PKG-INFO
fastools.egg-info/SOURCES.txt
fastools.egg-info/dependency_links.txt
fastools.egg-info/entry_points.txt
fastools.egg-info/not-zip-safe
fastools.egg-info/requires.txt
fastools.egg-info/top_level.txt