Metadata-Version: 2.1
Name: fastools
Version: 1.1.5
Summary: FASTA/FASTQ analysis and manipulation toolkit.
Home-page: https://git.lumc.nl/j.f.j.laros/fastools
Author: Jeroen F.J. Laros
Author-email: J.F.J.Laros@lumc.nl
License: MIT
Keywords: bioinformatics
Platform: UNKNOWN
Classifier: Development Status :: 4 - Beta
Classifier: Intended Audience :: Science/Research
Classifier: Intended Audience :: Developers
Classifier: Operating System :: OS Independent
Classifier: Programming Language :: Python
Classifier: Topic :: Scientific/Engineering
License-File: LICENSE.md
